Data_Generator_LRT.py
__init__.py
Data_Generator_LRT-0.0.4.dist-info/METADATA
Data_Generator_LRT-0.0.4.dist-info/WHEEL
Data_Generator_LRT-0.0.4.dist-info/top_level.txt
Data_Generator_LRT-0.0.4.dist-info/RECORD
