Metadata-Version: 2.1
Name: Data-Generator-LRT
Version: 0.0.4
Requires-Dist: numpy
